pyradixtree/__init__.py
pyradixtree/rax.py
pyradixtree/__pycache__/__init__.cpython-311.pyc
pyradixtree/__pycache__/rax.cpython-311.pyc
pyradixtree-0.0.1.dist-info/LICENSE
pyradixtree-0.0.1.dist-info/METADATA
pyradixtree-0.0.1.dist-info/WHEEL
pyradixtree-0.0.1.dist-info/top_level.txt
pyradixtree-0.0.1.dist-info/RECORD
