Metadata-Version: 2.1
Name: pyradixtree
Version: 0.0.1
Summary: pyradixtree, a python radix tree implementation
Home-page: https://github.com/wudilun123/pyradixtree.git
Author: zhang dapao
Author-email: wudilun123@gmail.com
License: MIT
Classifier: Programming Language :: Python :: 3.8
Classifier: License :: OSI Approved :: MIT License
Classifier: Operating System :: OS Independent
Classifier: Intended Audience :: Developers
Requires-Python: >=3.8
License-File: LICENSE
